MANIFEST.in
setup.py
activipy/__init__.py
activipy/activitystreams2-context.jsonld
activipy/core.py
activipy/testcli.py
activipy/vocab.py
activipy.egg-info/PKG-INFO
activipy.egg-info/SOURCES.txt
activipy.egg-info/dependency_links.txt
activipy.egg-info/entry_points.txt
activipy.egg-info/not-zip-safe
activipy.egg-info/requires.txt
activipy.egg-info/top_level.txt
activipy/demos/__init__.py
activipy/demos/checkup.py
activipy/demos/dbm.py