Metadata-Version: 1.1
Name: activipy
Version: 0.1
Summary: ActivityStreams 2.0 implementation and testing for Python
Home-page: UNKNOWN
Author: Christopher Allan Webber
Author-email: cwebber@dustycloud.org
License: Apache v2
Platform: UNKNOWN
Classifier: License :: OSI Approved :: Apache Software License
